ih2torrent.py
version.py
ih2torrent-0.1.17.dist-info/LICENSE.txt
ih2torrent-0.1.17.dist-info/METADATA
ih2torrent-0.1.17.dist-info/WHEEL
ih2torrent-0.1.17.dist-info/entry_points.txt
ih2torrent-0.1.17.dist-info/top_level.txt
ih2torrent-0.1.17.dist-info/RECORD
