Metadata-Version: 2.1
Name: ih2torrent
Version: 0.1.17
Summary: Convert a torrent infohash or magnet URI to a .torrent file using DHT and metadata protocol. Asyncio based.
Home-page: https://github.com/elektito/ih2torrent
Author: Mostafa Razavi
Author-email: mostafa@sepent.com
License: GPL
Download-URL: https://github.com/elektito/ih2torrent/tarball/0.1.17
Keywords: bittorrent,torrent,infohash,magnet,dht,metadata,metainfo,asyncio
Platform: UNKNOWN
Classifier: Programming Language :: Python :: 3
License-File: LICENSE.txt
Requires-Dist: aiodns (==3.0.0)
Requires-Dist: bencodepy (==0.9.5)
